{
  "$schema": "../../../schema/mxf-room.schema.json",
  "id": 169,
  "name": "Habitation Deck",
  "area": "MDK",
  "subarea": "Upper Main Deck",
  "roomImageFile": "MDK Room 27.png",
  "roomAddress": "0x0",
  "roomEnvironments": [
    {
      "heated": false,
      "cold": false
    }
  ],
  "mapTileMask": [
    [
      0
    ]
  ],
  "nodes": [
    {
      "id": 49,
      "idMinorItemPlm": "0x03",
      "name": "Energy Tank",
      "nodeType": "item",
      "nodeSubType": "visible",
      "nodeItem": "ETank",
      "nodeAddress": "0x7D3F0",
      "mapTileX": 29,
      "mapTileY": 11,
      "note": "Bottom-Left"
    },
    {
      "id": 50,
      "idMinorItemPlm": "0x04",
      "name": "Energy Tank",
      "nodeType": "item",
      "nodeSubType": "visible",
      "nodeItem": "ETank",
      "nodeAddress": "0x7D3F6",
      "mapTileX": 31,
      "mapTileY": 11,
      "note": "Bottom-Right"
    },
    {
      "id": 551,
      "name": "North-West Door",
      "nodeType": "door",
      "nodeSubType": "blue",
      "nodeAddress": "0x0",
      "doorOrientation": "left",
      "doorEnvironments": [
        {
          "physics": "air"
        }
      ]
    },
    {
      "id": 552,
      "name": "North-East Door",
      "nodeType": "door",
      "nodeSubType": "blue",
      "nodeAddress": "0x0",
      "doorOrientation": "right",
      "doorEnvironments": [
        {
          "physics": "air"
        }
      ]
    },
    {
      "id": 553,
      "name": "South Door",
      "nodeType": "door",
      "nodeSubType": "blue",
      "nodeAddress": "0x0",
      "doorOrientation": "down",
      "doorEnvironments": [
        {
          "physics": "air"
        }
      ]
    }
  ],
  "enemies": [],
  "links": [],
  "strats": [],
  "notables": [],
  "nextStratId": 1,
  "nextNotableId": 1
}