{
  "$schema": "../../../schema/mxf-room.schema.json",
  "id": 204,
  "name": "Nocturnal Crossroads",
  "area": "NOC",
  "subarea": "Lower NOC",
  "roomEnvironments": [
    {
      "heated": false,
      "cold": false
    }
  ],
  "mapTileMask": [
    [
      0
    ]
  ],
  "nodes": [
    {
      "id": 1,
      "name": "Top-Left Door",
      "nodeType": "door",
      "nodeSubType": "blue",
      "geometry": [
        {
          "shape": "rect",
          "x": 256,
          "y": 96,
          "w": 48,
          "h": 64
        }
      ],
      "color": "#ffffff",
      "nodeAddress": "0x0",
      "doorOrientation": "left",
      "doorEnvironments": [
        {
          "physics": "air"
        }
      ]
    },
    {
      "id": 2,
      "name": "Top-Right Door",
      "nodeType": "door",
      "nodeSubType": "blue",
      "geometry": [
        {
          "shape": "rect",
          "x": 464,
          "y": 96,
          "w": 48,
          "h": 64
        }
      ],
      "color": "#ffffff",
      "nodeAddress": "0x0",
      "doorOrientation": "right",
      "doorEnvironments": [
        {
          "physics": "air"
        }
      ]
    },
    {
      "id": 3,
      "name": "Right-Lower Door",
      "nodeType": "door",
      "nodeSubType": "blue",
      "geometry": [
        {
          "shape": "rect",
          "x": 456,
          "y": 592,
          "w": 48,
          "h": 64
        }
      ],
      "color": "#ffffff",
      "nodeAddress": "0x0",
      "doorOrientation": "right",
      "doorEnvironments": [
        {
          "physics": "air"
        }
      ]
    },
    {
      "id": 4,
      "name": "Bottom-Left Door",
      "nodeType": "door",
      "nodeSubType": "blue",
      "geometry": [
        {
          "shape": "rect",
          "x": 264,
          "y": 864,
          "w": 48,
          "h": 64
        }
      ],
      "color": "#ffffff",
      "nodeAddress": "0x0",
      "doorOrientation": "left",
      "doorEnvironments": [
        {
          "physics": "air"
        }
      ]
    },
    {
      "id": 6,
      "idMinorItemPlm": "0x6A",
      "name": "Nocturnal Crossroads - Missile Tank",
      "nodeType": "item",
      "nodeSubType": "visible",
      "geometry": [
        {
          "shape": "rect",
          "x": 112,
          "y": 672,
          "w": 16,
          "h": 16
        }
      ],
      "color": "#37c90e",
      "nodeItem": "Missile",
      "nodeAddress": "0x7E2A0",
      "mapTileX": 22,
      "mapTileY": 13
    },
    {
      "id": 5,
      "name": "Nocturnal Crossroads - NOC Aux Power Cell",
      "nodeType": "item",
      "nodeSubType": "visible",
      "geometry": [
        {
          "shape": "rect",
          "x": 640,
          "y": 928,
          "w": 16,
          "h": 16
        }
      ],
      "color": "#8d0cad",
      "nodeItem": "Major",
      "nodeAddress": "0x0",
      "note": "Jump through the wall at the bottom-right of the room"
    },
    {
      "id": 7,
      "name": "Above Grapple Blocks",
      "nodeType": "junction",
      "nodeSubType": "visible",
      "geometry": [
        {
          "shape": "rect",
          "x": 320,
          "y": 288,
          "w": 72,
          "h": 32
        }
      ],
      "color": "#0000ff"
    }
  ],
  "obstacles": [
    {
      "name": "Power Bomb Blocks",
      "obstacleType": "inanimate",
      "id": "A"
    },
    {
      "name": "Screw Attack Blocks",
      "obstacleType": "inanimate",
      "id": "B"
    },
    {
      "name": "Crumble Blocks",
      "obstacleType": "inanimate",
      "id": "C"
    }
  ],
  "strats": [
    {
      "name": "Base",
      "link": [
        1,
        1
      ],
      "requires": [
        {
          "ammo": {
            "type": "PowerBomb",
            "count": 1
          }
        }
      ],
      "clearsObstacles": [
        "A"
      ]
    },
    {
      "name": "Base",
      "link": [
        1,
        1
      ],
      "requires": [
        "ScrewAttack"
      ],
      "clearsObstacles": [
        "B"
      ]
    },
    {
      "name": "Base",
      "link": [
        1,
        2
      ],
      "requires": [
        {
          "obstaclesCleared": [
            "B"
          ]
        }
      ]
    },
    {
      "name": "Base",
      "link": [
        2,
        1
      ],
      "requires": [
        {
          "obstaclesCleared": [
            "B"
          ]
        }
      ]
    },
    {
      "name": "Base",
      "link": [
        2,
        2
      ],
      "requires": [
        "ScrewAttack"
      ],
      "clearsObstacles": [
        "B"
      ]
    },
    {
      "name": "Base",
      "link": [
        2,
        3
      ],
      "resetsObstacles": [
        "C"
      ],
      "requires": []
    },
    {
      "name": "Base",
      "link": [
        3,
        4
      ],
      "requires": [
        {
          "or": [
            "canCarefulJump",
            "canWalljump"
          ]
        }
      ]
    },
    {
      "name": "Base",
      "link": [
        3,
        6
      ],
      "collectsItems": [
        6
      ],
      "setsFlags": [
        "f_NocturnalCrossroads_MissileTank_Collected"
      ],
      "requires": []
    },
    {
      "name": "Base",
      "link": [
        3,
        7
      ],
      "requires": [
        {
          "or": [
            "SpaceJump",
            {
              "and": [
                "Grapple",
                "canWalljump"
              ]
            },
            "canIBJ"
          ]
        }
      ]
    },
    {
      "name": "Base",
      "link": [
        4,
        3
      ],
      "requires": [
        "canCarefulJump"
      ]
    },
    {
      "name": "Base",
      "link": [
        4,
        5
      ],
      "requires": [
        {
          "and": [
            "f_HardMode",
            {
              "or": [
                "canCarefulJump",
                "canWalljump"
              ]
            }
          ]
        }
      ],
      "collectsItems": [
        5
      ],
      "setsFlags": [
        "f_NOC_PowerCellAcquired"
      ]
    },
    {
      "name": "Base",
      "link": [
        5,
        4
      ],
      "requires": [
        {
          "or": [
            "canCarefulJump",
            "canWalljump"
          ]
        }
      ]
    },
    {
      "name": "Base",
      "link": [
        6,
        3
      ],
      "requires": []
    },
    {
      "name": "Base",
      "link": [
        7,
        1
      ],
      "requires": [
        {
          "and": [
            {
              "obstaclesCleared": [
                "A"
              ]
            },
            {
              "or": [
                "canIBJ",
                "canConsecutiveAlternatingWallJump",
                "SpaceJump",
                {
                  "and": [
                    "SuperJump",
                    "canWalljump"
                  ]
                }
              ]
            }
          ]
        }
      ]
    },
    {
      "name": "Base",
      "link": [
        7,
        7
      ],
      "requires": [
        {
          "ammo": {
            "type": "PowerBomb",
            "count": 1
          }
        }
      ],
      "clearsObstacles": [
        "A"
      ]
    }
  ],
  "roomImageFile": "NOC Room 7AE00.jpg",
  "roomAddress": "0x7AE00",
  "nextStratId": 1,
  "nextNotableId": 1
}