{
  "$schema": "../../../schema/mxf-room.schema.json",
  "id": 216,
  "name": "L-X-NOC Tube",
  "area": "NOC",
  "subarea": "Upper NOC",
  "roomEnvironments": [
    {
      "heated": false,
      "cold": false
    }
  ],
  "mapTileMask": [
    [
      0
    ]
  ],
  "nodes": [
    {
      "id": 1,
      "name": "Left Door",
      "nodeType": "door",
      "nodeSubType": "blue",
      "geometry": [
        {
          "shape": "rect",
          "x": 0,
          "y": 96,
          "w": 48,
          "h": 64
        }
      ],
      "color": "#ffffff",
      "nodeAddress": "0x0",
      "doorOrientation": "left",
      "doorEnvironments": [
        {
          "physics": "air"
        }
      ]
    },
    {
      "id": 2,
      "name": "Right-Lower Door",
      "nodeType": "door",
      "nodeSubType": "blue",
      "geometry": [
        {
          "shape": "rect",
          "x": 464,
          "y": 128,
          "w": 48,
          "h": 64
        }
      ],
      "color": "#ffffff",
      "nodeAddress": "0x0",
      "doorOrientation": "right",
      "doorEnvironments": [
        {
          "physics": "air"
        }
      ]
    }
  ],
  "obstacles": [
    {
      "name": "Super Missile Blocks",
      "obstacleType": "inanimate",
      "id": "A"
    }
  ],
  "strats": [
    {
      "name": "Destroy Super Missile Blocks",
      "link": [
        1,
        1
      ],
      "requires": [
        {
          "or": [
            {
              "ammo": {
                "type": "Super",
                "count": 1
              }
            },
            {
              "ammo": {
                "type": "Diffusion",
                "count": 1
              }
            }
          ]
        }
      ],
      "clearsObstacles": [
        "A"
      ]
    },
    {
      "name": "Base",
      "link": [
        1,
        2
      ],
      "requires": [
        {
          "and": [
            {
              "obstaclesCleared": [
                "A"
              ]
            },
            "SpaceJump"
          ]
        }
      ]
    },
    {
      "name": "Base",
      "link": [
        2,
        1
      ],
      "requires": [
        {
          "and": [
            {
              "obstaclesCleared": [
                "A"
              ]
            },
            "SpaceJump"
          ]
        }
      ]
    },
    {
      "name": "Destroy Super Missile Blocks",
      "link": [
        2,
        2
      ],
      "requires": [
        {
          "or": [
            {
              "ammo": {
                "type": "Super",
                "count": 1
              }
            },
            {
              "ammo": {
                "type": "Diffusion",
                "count": 1
              }
            }
          ]
        }
      ],
      "clearsObstacles": [
        "A"
      ]
    }
  ],
  "roomImageFile": "NOC Room 78700.jpg",
  "roomAddress": "0x78700",
  "nextStratId": 1,
  "nextNotableId": 1
}