{
  "$schema": "../../../schema/mxf-room.schema.json",
  "id": 218,
  "name": "Mochtroid Tower",
  "area": "NOC",
  "subarea": "Upper NOC",
  "roomEnvironments": [
    {
      "heated": false,
      "cold": false
    }
  ],
  "mapTileMask": [
    [
      0
    ]
  ],
  "nodes": [
    {
      "id": 1,
      "name": "Top-Left Door",
      "nodeType": "door",
      "nodeSubType": "blue",
      "geometry": [
        {
          "shape": "rect",
          "x": 0,
          "y": 96,
          "w": 48,
          "h": 64
        }
      ],
      "color": "#ffffff",
      "nodeAddress": "0x0",
      "doorOrientation": "left",
      "doorEnvironments": [
        {
          "physics": "air"
        }
      ]
    },
    {
      "id": 2,
      "name": "Left Door",
      "nodeType": "door",
      "nodeSubType": "blue",
      "nodeAddress": "0x0",
      "doorOrientation": "left",
      "geometry": [
        {
          "shape": "rect",
          "x": 0,
          "y": 352,
          "w": 48,
          "h": 64
        }
      ],
      "color": "#ffffff",
      "doorEnvironments": [
        {
          "physics": "lowGrav"
        }
      ],
      "useImplicitDoorUnlocks": true,
      "mapTileMask": [
        [
          0,
          0,
          0,
          0
        ],
        [
          0,
          0,
          0,
          0
        ],
        [
          0,
          0,
          0,
          0
        ],
        [
          0,
          0,
          0,
          0
        ]
      ]
    },
    {
      "id": 3,
      "name": "Right-Lower Door",
      "nodeType": "door",
      "nodeSubType": "blue",
      "nodeAddress": "0x0",
      "doorOrientation": "right",
      "geometry": [
        {
          "shape": "rect",
          "x": 208,
          "y": 864,
          "w": 48,
          "h": 64
        }
      ],
      "color": "#ffffff",
      "doorEnvironments": [
        {
          "physics": "lowGrav"
        }
      ],
      "useImplicitDoorUnlocks": true,
      "mapTileMask": [
        [
          0,
          0,
          0,
          0
        ],
        [
          0,
          0,
          0,
          0
        ],
        [
          0,
          0,
          0,
          0
        ],
        [
          0,
          0,
          0,
          0
        ]
      ]
    },
    {
      "id": 4,
      "name": "Bottom-Left Door",
      "nodeType": "door",
      "nodeSubType": "blue",
      "nodeAddress": "0x0",
      "doorOrientation": "left",
      "geometry": [
        {
          "shape": "rect",
          "x": 0,
          "y": 1120,
          "w": 48,
          "h": 64
        }
      ],
      "color": "#ffffff",
      "doorEnvironments": [
        {
          "physics": "lowGrav"
        }
      ],
      "useImplicitDoorUnlocks": true,
      "mapTileMask": [
        [
          0,
          0,
          0,
          0
        ],
        [
          0,
          0,
          0,
          0
        ],
        [
          0,
          0,
          0,
          0
        ],
        [
          0,
          0,
          0,
          0
        ]
      ]
    },
    {
      "id": 5,
      "name": "Bottom-Right Door",
      "nodeType": "door",
      "nodeSubType": "blue",
      "geometry": [
        {
          "shape": "rect",
          "x": 208,
          "y": 1120,
          "w": 48,
          "h": 64
        }
      ],
      "color": "#ffffff",
      "nodeAddress": "0x0",
      "doorOrientation": "right",
      "doorEnvironments": [
        {
          "physics": "air"
        }
      ]
    },
    {
      "id": 6,
      "name": "Grapple Climb Junction",
      "nodeType": "junction",
      "nodeSubType": "visible",
      "geometry": [
        {
          "shape": "rect",
          "x": 48,
          "y": 880,
          "w": 40,
          "h": 56
        }
      ],
      "color": "#0000ff"
    }
  ],
  "enemies": [
    {
      "groupName": "Upper Mochtroid-X",
      "enemyName": "Mochtroid-X",
      "quantity": 2,
      "betweenNodes": [
        1,
        2
      ],
      "id": "e1"
    },
    {
      "groupName": "Lower Mochtroid-X",
      "enemyName": "Mochtroid-X",
      "quantity": 3,
      "betweenNodes": [
        4,
        6
      ],
      "id": "e2"
    },
    {
      "groupName": "Middle Mochtroid-X",
      "enemyName": "Mochtroid-X",
      "quantity": 2,
      "betweenNodes": [
        2,
        6
      ],
      "id": "e3"
    },
    {
      "groupName": "Lowest Mochtroid-X",
      "enemyName": "Mochtroid-X",
      "quantity": 1,
      "betweenNodes": [
        4,
        5
      ],
      "id": "e4"
    }
  ],
  "strats": [
    {
      "name": "Base (Suitless)",
      "link": [
        1,
        2
      ],
      "requires": [
        {
          "and": [
            "canSuitlessWaterRoom",
            {
              "enemyKill": {
                "enemies": [
                  [
                    "e1"
                  ]
                ]
              }
            }
          ]
        }
      ]
    },
    {
      "name": "Base",
      "link": [
        1,
        2
      ],
      "requires": [
        "h_navigateLowGrav"
      ]
    },
    {
      "name": "Base (Suitless)",
      "link": [
        2,
        1
      ],
      "requires": [
        {
          "and": [
            "canSuitlessWaterRoom",
            "canLongIBJ",
            "canSuitlessUnderwaterIBJ",
            {
              "enemyKill": {
                "enemies": [
                  [
                    "e1"
                  ]
                ]
              }
            }
          ]
        }
      ]
    },
    {
      "name": "Base",
      "link": [
        2,
        1
      ],
      "requires": [
        {
          "and": [
            {
              "or": [
                "Gravity"
              ]
            },
            {
              "or": [
                "canLongIBJ",
                "canConsecutiveAlternatingWallJump",
                "SpaceJump"
              ]
            }
          ]
        }
      ]
    },
    {
      "name": "Base",
      "link": [
        2,
        5
      ],
      "requires": [
        "h_navigateLowGrav"
      ]
    },
    {
      "name": "Base",
      "link": [
        4,
        5
      ],
      "requires": [
        {
          "enemyKill": {
            "enemies": [
              [
                "e4"
              ]
            ]
          }
        }
      ]
    },
    {
      "name": "Base",
      "link": [
        5,
        3
      ],
      "requires": [
        {
          "and": [
            {
              "or": [
                "Gravity"
              ]
            },
            {
              "or": [
                "canIBJ",
                "SpaceJump",
                {
                  "and": [
                    {
                      "or": [
                        "canPreciseWalljump",
                        "canUseFrozenEnemies"
                      ]
                    }
                  ]
                }
              ]
            }
          ]
        }
      ]
    },
    {
      "name": "Spark up to Right-Lower Door",
      "devNote": "FIXME: Shinecharge Frames needs to be properly timed",
      "link": [
        5,
        3
      ],
      "entranceCondition": {
        "comeInShinecharged": {}
      },
      "requires": [
        {
          "and": [
            {
              "shinespark": {
                "frames": 23
              }
            },
            {
              "shineChargeFrames": 50
            }
          ]
        }
      ]
    },
    {
      "name": "Base",
      "link": [
        5,
        4
      ],
      "requires": [
        {
          "enemyKill": {
            "enemies": [
              [
                "e4"
              ]
            ]
          }
        }
      ]
    },
    {
      "name": "Base (Suitless)",
      "link": [
        5,
        6
      ],
      "requires": [
        {
          "and": [
            "canSuitlessWaterRoom",
            {
              "or": [
                "canTrickyGrappleJump",
                {
                  "and": [
                    "canIBJ",
                    {
                      "enemyKill": {
                        "enemies": [
                          [
                            "e2"
                          ]
                        ]
                      }
                    }
                  ]
                }
              ]
            },
            {
              "or": [
                {
                  "and": [
                    "canIBJ",
                    {
                      "enemyKill": {
                        "enemies": [
                          [
                            "e3"
                          ]
                        ]
                      }
                    }
                  ]
                },
                {
                  "enemyKill": {
                    "enemies": [
                      [
                        "e3"
                      ]
                    ]
                  }
                }
              ]
            }
          ]
        }
      ]
    },
    {
      "name": "Base",
      "link": [
        5,
        6
      ],
      "requires": [
        {
          "and": [
            {
              "or": [
                "canPreciseWalljump",
                "SpaceJump",
                "canIBJ",
                "SpaceJump"
              ]
            },
            {
              "or": [
                {
                  "and": [
                    {
                      "enemyKill": {
                        "enemies": [
                          [
                            "e2"
                          ]
                        ]
                      }
                    },
                    {
                      "enemyKill": {
                        "enemies": [
                          [
                            "e3"
                          ]
                        ]
                      }
                    }
                  ]
                }
              ]
            },
            {
              "or": [
                "SpaceJump",
                "Grapple",
                "canIBJ"
              ]
            },
            "h_navigateLowGrav"
          ]
        }
      ]
    },
    {
      "name": "Base (Suitless)",
      "link": [
        6,
        2
      ],
      "requires": [
        {
          "and": [
            "canSuitlessWaterRoom",
            {
              "or": [
                "canTrickyGrappleJump",
                {
                  "and": [
                    "canIBJ",
                    {
                      "enemyKill": {
                        "enemies": [
                          [
                            "e2"
                          ]
                        ]
                      }
                    }
                  ]
                }
              ]
            },
            {
              "or": [
                {
                  "and": [
                    "canIBJ",
                    {
                      "enemyKill": {
                        "enemies": [
                          [
                            "e3"
                          ]
                        ]
                      }
                    }
                  ]
                },
                {
                  "enemyKill": {
                    "enemies": [
                      [
                        "e3"
                      ]
                    ]
                  }
                }
              ]
            }
          ]
        }
      ]
    },
    {
      "name": "Base",
      "link": [
        6,
        2
      ],
      "requires": [
        {
          "and": [
            {
              "or": [
                "canPreciseWalljump",
                "SpaceJump",
                "canIBJ",
                "SpaceJump"
              ]
            },
            {
              "or": [
                {
                  "and": [
                    {
                      "enemyKill": {
                        "enemies": [
                          [
                            "e2"
                          ]
                        ]
                      }
                    },
                    {
                      "enemyKill": {
                        "enemies": [
                          [
                            "e3"
                          ]
                        ]
                      }
                    }
                  ]
                }
              ]
            },
            {
              "or": [
                "SpaceJump",
                "Grapple",
                "canIBJ"
              ]
            },
            "h_navigateLowGrav"
          ]
        }
      ]
    }
  ],
  "roomImageFile": "NOC Room 78E00.jpg",
  "roomAddress": "0x78E00",
  "nextStratId": 1,
  "nextNotableId": 1
}